tcvdb_text/__init__.py
tcvdb_text/data/bm25_en_default.json
tcvdb_text/data/bm25_zh_default.json
tcvdb_text/data/stopwords.txt
tcvdb_text/data/userdict_example.txt
tcvdb_text/encoder/__init__.py
tcvdb_text/encoder/base_encoder.py
tcvdb_text/encoder/bm25.py
tcvdb_text/hash/__init__.py
tcvdb_text/hash/hash.py
tcvdb_text/tokenizer/__init__.py
tcvdb_text/tokenizer/base_tokenizer.py
tcvdb_text/tokenizer/jieba_tokenizer.py
tcvdb_text-1.1.1.dist-info/METADATA
tcvdb_text-1.1.1.dist-info/WHEEL
tcvdb_text-1.1.1.dist-info/top_level.txt
tcvdb_text-1.1.1.dist-info/RECORD
